pgdiff/__init__.py
pgdiff/cli.py
pgdiff/diff.py
pgdiff/helpers.py
pgdiff/inspect.py
pgdiff/objects.py
pgdiff/py.typed
pgdiff/sync.py
pgdiff/utils.py
sql/dependencies.sql
sql/enums.sql
sql/extensions.sql
sql/functions.sql
sql/indices.sql
sql/relations.sql
sql/schemas.sql
sql/sequences.sql
sql/tables.sql
sql/triggers.sql
sql/views.sql
pgdiff-0.1.20.post1.dist-info/entry_points.txt
pgdiff-0.1.20.post1.dist-info/WHEEL
pgdiff-0.1.20.post1.dist-info/METADATA
pgdiff-0.1.20.post1.dist-info/RECORD
